nicolasbancel_de_toolkit/.env
nicolasbancel_de_toolkit/.envrc
nicolasbancel_de_toolkit/__init__.py
nicolasbancel_de_toolkit/main.py
nicolasbancel_de_toolkit/vm.py
nicolasbancel_de_toolkit-0.1.0.dist-info/entry_points.txt
nicolasbancel_de_toolkit-0.1.0.dist-info/WHEEL
nicolasbancel_de_toolkit-0.1.0.dist-info/METADATA
nicolasbancel_de_toolkit-0.1.0.dist-info/RECORD
