Metadata-Version: 2.1
Name: nicolasbancel-de-toolkit
Version: 0.1.0
Summary: 
Author: Nicolas Bancel
Author-email: nicolas.bancel@gmail.com
Requires-Python: >=3.8,<4.0
Classifier: Programming Language :: Python :: 3
Classifier: Programming Language :: Python :: 3.8
Classifier: Programming Language :: Python :: 3.9
Classifier: Programming Language :: Python :: 3.10
Classifier: Programming Language :: Python :: 3.11
Requires-Dist: click (>=8.1.3,<9.0.0)
